nonebot_plugin_imagemaster/__init__.py
nonebot_plugin_imagemaster/bot_main.py
nonebot_plugin_imagemaster/image_editor.py
nonebot_plugin_imagemaster/ocr.py1
nonebot_plugin_imagemaster/songti.ttf
nonebot_plugin_imagemaster/图片1.png
nonebot_plugin_imagemaster-1.0.8.dist-info/LICENSE
nonebot_plugin_imagemaster-1.0.8.dist-info/METADATA
nonebot_plugin_imagemaster-1.0.8.dist-info/WHEEL
nonebot_plugin_imagemaster-1.0.8.dist-info/RECORD
