Metadata-Version: 2.1
Name: nonebot-plugin-imagemaster
Version: 1.0.8
Summary: 提供多种图像处理功能的bot插件
Author: phquathi
Author-email: yangziqi233@gmail.com
Requires-Python: >=3.7,<4.0
Classifier: Programming Language :: Python :: 3
Classifier: Programming Language :: Python :: 3.7
Classifier: Programming Language :: Python :: 3.8
Classifier: Programming Language :: Python :: 3.9
Classifier: Programming Language :: Python :: 3.10
Classifier: Programming Language :: Python :: 3.11
Classifier: Programming Language :: Python :: 3.12
Requires-Dist: Pillow (>=8.0.0,<9.0.0)
Requires-Dist: aiohttp (>=3.7.4,<4.0.0)
Requires-Dist: nonebot-adapter-onebot (>=2.0.0,<3.0.0)
Requires-Dist: nonebot-plugin-apscheduler (>=0.4.0,<0.5.0)
Requires-Dist: nonebot2 (>=2.0.0,<3.0.0)
Requires-Dist: numpy (>=1.0.0,<2.0.0)
Requires-Dist: opencv-python (>=4.0.0,<5.0.0)
